uboat.py
uboat-0.1.1.dist-info/LICENSE
uboat-0.1.1.dist-info/METADATA
uboat-0.1.1.dist-info/WHEEL
uboat-0.1.1.dist-info/top_level.txt
uboat-0.1.1.dist-info/RECORD
